leaks/__init__.py
leaks/courses.py
leaks/utils.py
leaks-0.1.0.dist-info/METADATA
leaks-0.1.0.dist-info/WHEEL
leaks-0.1.0.dist-info/top_level.txt
leaks-0.1.0.dist-info/RECORD
