Metadata-Version: 2.4
Name: leaks
Version: 0.1.0
Summary: Una biblioteca para consultar cursos
Home-page: https://hack4u.io
Author: Maximiliano Garcia
Dynamic: author
Dynamic: description
Dynamic: description-content-type
Dynamic: home-page
Dynamic: summary
